fast_clean/__init__.py
fast_clean/container.py
fast_clean/db.py
fast_clean/depends.py
fast_clean/enums.py
fast_clean/exceptions.py
fast_clean/loggers.py
fast_clean/middleware.py
fast_clean/models.py
fast_clean/py.typed
fast_clean/redis.py
fast_clean/settings.py
fast_clean/contrib/__init__.py
fast_clean/contrib/healthcheck/__init__.py
fast_clean/contrib/healthcheck/router.py
fast_clean/contrib/healthcheck/schemas.py
fast_clean/contrib/monitoring/__init__.py
fast_clean/contrib/sentry/__init__.py
fast_clean/contrib/sentry/enums.py
fast_clean/contrib/sentry/sentry.py
fast_clean/contrib/sqlalchemy_utils/__init__.py
fast_clean/contrib/sqlalchemy_utils/utils.py
fast_clean/repositories/__init__.py
fast_clean/repositories/cache/__init__.py
fast_clean/repositories/cache/in_memory.py
fast_clean/repositories/cache/redis.py
fast_clean/repositories/crud/__init__.py
fast_clean/repositories/crud/db.py
fast_clean/repositories/crud/in_memory.py
fast_clean/repositories/crud/type_vars.py
fast_clean/repositories/http/__init__.py
fast_clean/repositories/http/auths.py
fast_clean/repositories/http/repositories.py
fast_clean/repositories/settings/__init__.py
fast_clean/repositories/settings/enums.py
fast_clean/repositories/settings/env.py
fast_clean/repositories/settings/exceptions.py
fast_clean/repositories/settings/type_vars.py
fast_clean/repositories/storage/__init__.py
fast_clean/repositories/storage/enums.py
fast_clean/repositories/storage/local.py
fast_clean/repositories/storage/reader.py
fast_clean/repositories/storage/s3.py
fast_clean/repositories/storage/schemas.py
fast_clean/schemas/__init__.py
fast_clean/schemas/auths.py
fast_clean/schemas/exceptions.py
fast_clean/schemas/pagination.py
fast_clean/schemas/repository.py
fast_clean/schemas/request_response.py
fast_clean/services/__init__.py
fast_clean/services/lock.py
fast_clean/services/seed.py
fast_clean/services/transaction.py
fast_clean/services/cryptography/__init__.py
fast_clean/services/cryptography/aes.py
fast_clean-1.6.0.dist-info/METADATA
fast_clean-1.6.0.dist-info/WHEEL
fast_clean-1.6.0.dist-info/top_level.txt
fast_clean-1.6.0.dist-info/RECORD
